{
  "data_type": "coaching_model",
  "content": "Adaptive Leadership Coaching Model\n\nDeveloped by: Sam Chen\nVersion: 1.8\nLast Updated: October 2025\n\n[UNIQUE ISOLATION MARKER: SAM_MODEL_MARKER_T6U3]\n\n=== OVERVIEW ===\n\nThis coaching model is grounded in adaptive leadership theory, helping leaders navigate complex challenges that require people to change their values, beliefs, or behaviors. Unlike technical problems with known solutions, adaptive challenges require learning, experimentation, and leading through uncertainty.\n\n=== CORE PHILOSOPHY ===\n\nThe most important work of leadership happens in the face of adaptive challenges - problems that can't be solved with existing expertise or authority. Coaches help leaders diagnose challenges accurately, mobilize people for difficult change, and maintain their equilibrium while disturbing others productively.\n\n=== THE ADAPTIVE LEADERSHIP FRAMEWORK ===\n\n1. DIAGNOSE THE CHALLENGE\n   - Distinguish technical from adaptive challenges\n   - Understand the system dynamics at play\n   - Identify whose behavior needs to change\n   - Coaching Focus: Accurate problem diagnosis\n   - Key Questions:\n     * Is this a problem you can solve with current knowledge?\n     * Who needs to learn or change for this to be resolved?\n     * What are you/others protecting that prevents progress?\n\n2. MANAGE SELF\n   - Stay connected to purpose under pressure\n   - Maintain perspective on the system\n   - Regulate emotional responses\n   - Coaching Focus: Self-awareness and self-regulation\n   - Key Questions:\n     * What's getting triggered for you in this situation?\n     * How are you managing your own anxiety?\n     * What's your purpose in this leadership moment?\n\n3. ENERGIZE OTHERS\n   - Create holding environments for productive conflict\n   - Regulate the heat (enough to motivate, not overwhelm)\n   - Give work back to the people who need to do it\n   - Coaching Focus: Building change readiness\n   - Key Questions:\n     * How are you creating safety for difficult conversations?\n     * Where might you be doing work that belongs to others?\n     * What's the right amount of disequilibrium for your team?\n\n4. INTERVENE SKILLFULLY\n   - Make strategic interventions\n   - Speak from the balcony and the dance floor\n   - Protect voices of dissent\n   - Coaching Focus: Strategic action in complexity\n   - Key Questions:\n     * What intervention would shift the system?\n     * Whose voice is missing from this conversation?\n     * How will you know if your intervention worked?\n\n=== SESSION STRUCTURE ===\n\nTypical Session Flow (60 minutes):\n\n1. System Check-in (10 min)\n   - What's happening in your system right now?\n   - Where is the adaptive challenge showing up?\n   - How are you experiencing it personally?\n\n2. Diagnosis Deep-Dive (20 min)\n   - Explore the challenge through multiple stakeholder perspectives\n   - Distinguish technical vs. adaptive components\n   - Map the system dynamics and competing commitments\n\n3. Intervention Design (20 min)\n   - What experiments could you run?\n   - How will you manage yourself through this?\n   - What support structures do you need?\n\n4. Commitment and Reflection (10 min)\n   - What's your next leadership move?\n   - What will you pay attention to?\n   - What might you learn from this experiment?\n\n=== EVALUATION CRITERIA ===\n\nSession Quality Indicators:\n\n1. Diagnostic Accuracy\n   - Did we correctly identify technical vs. adaptive elements?\n   - Did we surface multiple perspectives on the challenge?\n\n2. Self-Management Focus\n   - Did we explore the client's internal experience?\n   - Did we strengthen their capacity for self-regulation?\n\n3. Systems Thinking\n   - Did we consider broader system dynamics?\n   - Did we identify leverage points for intervention?\n\n4. Experimental Mindset\n   - Did we frame actions as experiments to learn from?\n   - Did we build in reflection and adjustment?\n\n=== KEY PRINCIPLES ===\n\n1. Get on the Balcony\n   - Maintain perspective while in the action\n   - See patterns, not just events\n\n2. Identify the Adaptive Challenge\n   - Not every problem requires change\n   - Focus energy where real learning is needed\n\n3. Regulate Distress\n   - Too much stress = shutdown; too little = complacency\n   - Find the productive zone of disequilibrium\n\n4. Give the Work Back\n   - Leaders can't do adaptive work for others\n   - Create conditions where people can own their change\n\n5. Protect Voices from Below\n   - Dissent often carries important information\n   - Surface perspectives the system wants to silence\n\n=== COMMON ADAPTIVE CHALLENGES ===\n\nOrganizational:\n- Culture change initiatives\n- Digital transformation\n- Mergers and acquisitions\n- Restructuring and reorgs\n\nLeadership:\n- Role transitions (IC to manager, manager to executive)\n- Managing up in dysfunctional systems\n- Leading without formal authority\n- Building diverse and inclusive teams\n\nPersonal:\n- Work-life integration\n- Values conflicts\n- Career pivots\n- Managing competing loyalties\n\n=== RESOURCES ===\n\n- Heifetz: Leadership Without Easy Answers\n- Heifetz & Linsky: Leadership on the Line\n- Heifetz, Grashow & Linsky: The Practice of Adaptive Leadership\n- Kegan & Lahey: An Everyone Culture",
  "metadata": {
    "model_name": "Adaptive Leadership Coaching Model",
    "model_type": "theory_of_change",
    "version": "1.8",
    "coach_id": "550e8400-e29b-41d4-a716-446655440011",
    "visibility_level": "coach_only",
    "key_principles": [
      "Get on the Balcony",
      "Identify the Adaptive Challenge",
      "Regulate Distress",
      "Give the Work Back",
      "Protect Voices from Below"
    ],
    "evaluation_criteria": [
      "Diagnostic Accuracy",
      "Self-Management Focus",
      "Systems Thinking",
      "Experimental Mindset"
    ],
    "author": "Sam Chen",
    "tags": ["adaptive", "Heifetz", "complexity", "systems", "change"]
  }
}
