{
  "data_type": "company_doc",
  "content": "TechCorp Inc - Q4 2025 Strategic Plan\n\nConfidential - Internal Use Only\nDocument Version: 2.0\nLast Updated: October 15, 2025\nOwner: Emily Zhang, CEO\n\n[UNIQUE ISOLATION MARKER: TECHCORP_STRATEGY_MARKER_V6W2]\n\n=== EXECUTIVE SUMMARY ===\n\nTechCorp enters Q4 2025 with strong momentum following successful Series C funding ($85M). This strategic plan outlines our priorities for executing on growth targets while building sustainable competitive advantages. Our focus areas are: enterprise market expansion, product platform evolution, and organizational scaling.\n\n=== MARKET CONTEXT ===\n\nMarket Trends:\n- Enterprise SaaS spending continues growth trajectory (+18% YoY)\n- Increasing demand for AI-powered workflow automation\n- Consolidation among mid-market competitors\n- Rising customer expectations for integration capabilities\n\nCompetitive Landscape:\n- Primary: Acme Software (strong in mid-market), Vertex Systems (enterprise)\n- Emerging: Several AI-native startups gaining traction\n- Our Advantage: Superior integration platform + enterprise security credentials\n\n=== STRATEGIC PILLARS ===\n\nPILLAR 1: Enterprise Market Dominance\nOwner: David Kim, VP Sales\n\nObjectives:\n- Close 15 new enterprise accounts ($500K+ ACV)\n- Expand 10 existing accounts by 50%+ \n- Achieve $28M in Q4 bookings\n\nKey Initiatives:\n- Launch dedicated enterprise sales team (6 AEs)\n- Develop industry-specific solution packages\n- Expand partner channel (5 new SIs)\n- Implement account-based marketing program\n\nPILLAR 2: Product Platform Evolution\nOwner: VP Product\n\nObjectives:\n- Launch AI Assistant feature set (Beta: Nov 1, GA: Dec 15)\n- Achieve 95% platform reliability SLA\n- Reduce time-to-value for new customers by 50%\n\nKey Initiatives:\n- AI model training on customer workflow data\n- Self-service implementation wizard\n- Enhanced API documentation and developer portal\n- Mobile app refresh (iOS/Android)\n\nPILLAR 3: Organizational Excellence\nOwner: CEO (Emily Zhang)\n\nObjectives:\n- Scale team from 180 to 220 employees\n- Maintain culture scores above 4.2/5.0\n- Develop next generation of leaders\n\nKey Initiatives:\n- Executive coaching program (InsideOut Leadership)\n- Management training curriculum\n- DE&I metrics integration into performance reviews\n- Enhanced onboarding program\n\n=== FINANCIAL TARGETS ===\n\nQ4 2025 Targets:\n- Revenue: $24M (25% QoQ growth)\n- Gross Margin: 78%+\n- Net Revenue Retention: 125%\n- Customer Acquisition Cost: <$35K\n- LTV/CAC Ratio: >4.0\n\nInvestment Priorities:\n1. Sales & Marketing: 45% of spend\n2. R&D: 35% of spend\n3. G&A: 20% of spend\n\n=== RISK MANAGEMENT ===\n\nStrategic Risks:\n\n1. Execution Risk (High Impact, Medium Probability)\n   - Mitigation: Weekly executive review, clear ownership, buffer in timelines\n\n2. Competitive Response (Medium Impact, High Probability)\n   - Mitigation: Accelerate differentiated features, strengthen customer success\n\n3. Talent Risk (Medium Impact, Medium Probability)\n   - Mitigation: Competitive comp, development programs, culture investment\n\n4. Market Risk (High Impact, Low Probability)\n   - Mitigation: Diversified customer base, conservative financial planning\n\n=== SUCCESS METRICS ===\n\nLeading Indicators (Weekly):\n- Pipeline generated\n- Demo-to-opportunity conversion\n- Feature adoption rates\n- Employee engagement pulse\n\nLagging Indicators (Monthly):\n- Revenue achievement\n- Customer churn\n- Platform reliability\n- Team health scores\n\n=== GOVERNANCE ===\n\n- Weekly: Executive team strategy sync (Mondays)\n- Bi-weekly: Board update (written)\n- Monthly: All-hands strategy update\n- Quarterly: Board meeting and strategy review\n\nNext Review: November 1, 2025",
  "metadata": {
    "doc_type": "strategy",
    "doc_title": "TechCorp Inc Q4 2025 Strategic Plan",
    "doc_version": "2.0",
    "client_organization_id": "550e8400-e29b-41d4-a716-446655440201",
    "visibility_level": "org_visible",
    "fiscal_year": "2025",
    "quarter": "Q4",
    "author": "Emily Zhang, CEO",
    "last_updated": "2025-10-15T00:00:00Z",
    "confidentiality_level": "internal",
    "tags": ["strategy", "Q4", "2025", "enterprise", "growth", "Series C"]
  }
}
